alfredo/__init__.py
alfredo/cli.py
alfredo/descriptions.py
alfredo/format_si.py
alfredo/http.py
alfredo/http_service.py
alfredo/resource.py
alfredo/stream.py
alfredo/mixins/__init__.py
alfredo/mixins/lazy.py
alfredo/mixins/nested.py
alfredo_python-0.0.8.dist-info/LICENSE
alfredo_python-0.0.8.dist-info/METADATA
alfredo_python-0.0.8.dist-info/WHEEL
alfredo_python-0.0.8.dist-info/entry_points.txt
alfredo_python-0.0.8.dist-info/top_level.txt
alfredo_python-0.0.8.dist-info/RECORD
