Metadata-Version: 2.1
Name: alfredo-python
Version: 0.0.8
Summary: ..
Home-page: https://gitlab.atrio.io/atrio/alfredo-python-sdk
Author: Atrio, Inc.
Author-email: notify@atrio.io
License: LGPL 2.1
Keywords: alfredo python sdk
Platform: UNKNOWN
Classifier: Development Status :: 2 - Pre-Alpha
Classifier: Environment :: Console
Classifier: Intended Audience :: Developers
Classifier: Intended Audience :: Science/Research
Classifier: License :: OSI Approved :: GNU Lesser General Public License v2 or later (LGPLv2+)
Classifier: Operating System :: OS Independent
Classifier: Programming Language :: Python :: 2
Classifier: Programming Language :: Python :: 2.7
Classifier: Programming Language :: Python :: 3
Classifier: Programming Language :: Python :: 3.5
Classifier: Programming Language :: Python :: 3.6
Classifier: Programming Language :: Python :: 3.7
Classifier: Topic :: Internet
Classifier: Topic :: Software Development :: Libraries :: Python Modules
Requires-Dist: docopt
Requires-Dist: requests
Requires-Dist: requests-toolbelt
Requires-Dist: ruamel.yaml
